rtl/pwm8.v
module pwm8(

input clk,
input rst_n,
input tick_1k,

input [7:0] duty,

output reg out

);


reg [7:0] counter;


always @(posedge clk or negedge rst_n)
begin

if(!rst_n)
begin
counter <= 0;
out <= 0;
end

else if(tick_1k)
begin

counter <= counter + 1;

if(counter < duty)
    out <= 1;
else
    out <= 0;

end

end


endmodule

rtl/ctrl_fsm.v
module ctrl_fsm(

input clk,
input rst_n,

input pir,
input dark,
input temp_high,

input door_open,
input security,

input manual,


output reg [7:0] L0,

output reg [7:0] FAN,

output reg alarm

);


always @(posedge clk or negedge rst_n)
begin

if(!rst_n)
begin

L0 <= 0;
FAN <= 0;
alarm <= 0;

end


else
begin


// Safety highest priority

if(door_open && security)
begin

alarm <= 1;

L0 <= 255;
FAN <= 0;

end


// Manual override

else if(manual)
begin

alarm <= 0;

L0 <= 255;

end



// Automatic light

else if(pir && dark)
begin

alarm <= 0;

L0 <= 200;

end



// Temperature control

else if(temp_high)
begin

alarm <= 0;

FAN <= 255;

end



else
begin

L0 <= 0;

FAN <= 0;

alarm <= 0;

end


end

end


endmodule

rtl/clk_en.v
module clk_en #(parameter CLK_HZ=50000000,
                parameter TICK_HZ=1000)
(
input clk,
input rst_n,
output reg tick
);

localparam DIV = CLK_HZ/TICK_HZ;

reg [$clog2(DIV)-1:0] count;

always @(posedge clk or negedge rst_n)
begin
    if(!rst_n)
    begin
        count <= 0;
        tick <= 0;
    end
    else
    begin
        tick <= 0;

        if(count == DIV-1)
        begin
            count <= 0;
            tick <= 1;
        end
        else
            count <= count + 1;
    end
end

endmodule

rtl/top.v
module top(

input clk,
input reset,


input pir,
input dark,

input temp_high,

input door,

input security,

input manual,


output L0_PWM,

output FAN_PWM,

output RELAY,

output ALARM

);


wire tick;


clk_en clk_unit(

.clk(clk),

.rst_n(~reset),

.tick(tick)

);



wire [7:0] light_value;

wire [7:0] fan_value;



ctrl_fsm controller(

.clk(clk),

.rst_n(~reset),

.pir(pir),

.dark(dark),

.temp_high(temp_high),

.door_open(door),

.security(security),

.manual(manual),


.L0(light_value),

.FAN(fan_value),

.alarm(ALARM)

);



pwm8 light_pwm(

.clk(clk),

.rst_n(~reset),

.tick_1k(tick),

.duty(light_value),

.out(L0_PWM)

);



pwm8 fan_pwm(

.clk(clk),

.rst_n(~reset),

.tick_1k(tick),

.duty(fan_value),

.out(FAN_PWM)

);



assign RELAY = security;


endmodule

tb/home_tb.v
`timescale 1ns/1ps


module home_tb;


reg clk=0;

reg reset=1;


reg pir=0;

reg dark=0;

reg temp_high=0;

reg door=0;

reg security=0;

reg manual=0;


wire light;

wire fan;

wire relay;

wire alarm;



top DUT(

.clk(clk),

.reset(reset),

.pir(pir),

.dark(dark),

.temp_high(temp_high),

.door(door),

.security(security),

.manual(manual),


.L0_PWM(light),

.FAN_PWM(fan),

.RELAY(relay),

.ALARM(alarm)

);



always #5 clk=~clk;



initial
begin


$dumpfile("home.vcd");

$dumpvars(0,home_tb);



#50 reset=0;


// motion sensor

#100;

pir=1;

dark=1;


#200;

pir=0;



// temperature

#200;

temp_high=1;


#100;

temp_high=0;



// security alarm

#200;

security=1;

door=1;


#100;


// manual mode

security=0;

door=0;

manual=1;


#200;



$finish;


end


endmodule

home.vcd
$date
	Sun Jun 21 12:57:42 2026
$end
$version
	Icarus Verilog
$end
$timescale
	1ps
$end
$scope module home_tb $end
$var wire 1 ! relay $end
$var wire 1 " light $end
$var wire 1 # fan $end
$var wire 1 $ alarm $end
$var reg 1 % clk $end
$var reg 1 & dark $end
$var reg 1 ' door $end
$var reg 1 ( manual $end
$var reg 1 ) pir $end
$var reg 1 * reset $end
$var reg 1 + security $end
$var reg 1 , temp_high $end
$scope module DUT $end
$var wire 1 ! RELAY $end
$var wire 1 % clk $end
$var wire 1 & dark $end
$var wire 1 ' door $end
$var wire 1 ( manual $end
$var wire 1 ) pir $end
$var wire 1 * reset $end
$var wire 1 + security $end
$var wire 1 , temp_high $end
$var wire 1 - tick $end
$var wire 8 . light_value [7:0] $end
$var wire 8 / fan_value [7:0] $end
$var wire 1 " L0_PWM $end
$var wire 1 # FAN_PWM $end
$var wire 1 $ ALARM $end
$scope module clk_unit $end
$var wire 1 % clk $end
$var wire 1 0 rst_n $end
$var parameter 32 1 CLK_HZ $end
$var parameter 32 2 DIV $end
$var parameter 32 3 TICK_HZ $end
$var reg 16 4 count [15:0] $end
$var reg 1 - tick $end
$upscope $end
$scope module controller $end
$var wire 1 % clk $end
$var wire 1 & dark $end
$var wire 1 ' door_open $end
$var wire 1 ( manual $end
$var wire 1 ) pir $end
$var wire 1 5 rst_n $end
$var wire 1 + security $end
$var wire 1 , temp_high $end
$var reg 8 6 FAN [7:0] $end
$var reg 8 7 L0 [7:0] $end
$var reg 1 $ alarm $end
$upscope $end
$scope module fan_pwm $end
$var wire 1 % clk $end
$var wire 8 8 duty [7:0] $end
$var wire 1 9 rst_n $end
$var wire 1 - tick_1k $end
$var reg 8 : counter [7:0] $end
$var reg 1 # out $end
$upscope $end
$scope module light_pwm $end
$var wire 1 % clk $end
$var wire 8 ; duty [7:0] $end
$var wire 1 < rst_n $end
$var wire 1 - tick_1k $end
$var reg 8 = counter [7:0] $end
$var reg 1 " out $end
$upscope $end
$upscope $end
$upscope $end
$enddefinitions $end
$comment Show the parameter values. $end
$dumpall
b1111101000 3
b1100001101010000 2
b10111110101111000010000000 1
$end
#0
$dumpvars
bx =
0<
bx ;
bx :
09
bx 8
bx 7
bx 6
05
bx 4
00
bx /
bx .
x-
0,
0+
1*
0)
0(
0'
0&
0%
x$
x#
x"
0!
$end
#5000
0-
b0 4
0$
b0 /
b0 6
b0 8
b0 .
b0 7
b0 ;
0#
b0 :
0"
b0 =
1%
#10000
0%
#15000
1%
#20000
0%
#25000
1%
#30000
0%
#35000
1%
#40000
0%
#45000
1%
#50000
10
15
1<
19
0%
0*
#55000
b1 4
1%
#60000
0%
#65000
b10 4
1%
#70000
0%
#75000
b11 4
1%
#80000
0%
#85000
b100 4
1%
#90000
0%
#95000
b101 4
1%
#100000
0%
#105000
b110 4
1%
#110000
0%
#115000
b111 4
1%
#120000
0%
#125000
b1000 4
1%
#130000
0%
#135000
b1001 4
1%
#140000
0%
#145000
b1010 4
1%
#150000
0%
1&
1)
#155000
b1011 4
b11001000 .
b11001000 7
b11001000 ;
1%
#160000
0%
#165000
b1100 4
1%
#170000
0%
#175000
b1101 4
1%
#180000
0%
#185000
b1110 4
1%
#190000
0%
#195000
b1111 4
1%
#200000
0%
#205000
b10000 4
1%
#210000
0%
#215000
b10001 4
1%
#220000
0%
#225000
b10010 4
1%
#230000
0%
#235000
b10011 4
1%
#240000
0%
#245000
b10100 4
1%
#250000
0%
#255000
b10101 4
1%
#260000
0%
#265000
b10110 4
1%
#270000
0%
#275000
b10111 4
1%
#280000
0%
#285000
b11000 4
1%
#290000
0%
#295000
b11001 4
1%
#300000
0%
#305000
b11010 4
1%
#310000
0%
#315000
b11011 4
1%
#320000
0%
#325000
b11100 4
1%
#330000
0%
#335000
b11101 4
1%
#340000
0%
#345000
b11110 4
1%
#350000
0%
0)
#355000
b11111 4
b0 .
b0 7
b0 ;
1%
#360000
0%
#365000
b100000 4
1%
#370000
0%
#375000
b100001 4
1%
#380000
0%
#385000
b100010 4
1%
#390000
0%
#395000
b100011 4
1%
#400000
0%
#405000
b100100 4
1%
#410000
0%
#415000
b100101 4
1%
#420000
0%
#425000
b100110 4
1%
#430000
0%
#435000
b100111 4
1%
#440000
0%
#445000
b101000 4
1%
#450000
0%
#455000
b101001 4
1%
#460000
0%
#465000
b101010 4
1%
#470000
0%
#475000
b101011 4
1%
#480000
0%
#485000
b101100 4
1%
#490000
0%
#495000
b101101 4
1%
#500000
0%
#505000
b101110 4
1%
#510000
0%
#515000
b101111 4
1%
#520000
0%
#525000
b110000 4
1%
#530000
0%
#535000
b110001 4
1%
#540000
0%
#545000
b110010 4
1%
#550000
0%
1,
#555000
b110011 4
b11111111 /
b11111111 6
b11111111 8
1%
#560000
0%
#565000
b110100 4
1%
#570000
0%
#575000
b110101 4
1%
#580000
0%
#585000
b110110 4
1%
#590000
0%
#595000
b110111 4
1%
#600000
0%
#605000
b111000 4
1%
#610000
0%
#615000
b111001 4
1%
#620000
0%
#625000
b111010 4
1%
#630000
0%
#635000
b111011 4
1%
#640000
0%
#645000
b111100 4
1%
#650000
0%
0,
#655000
b111101 4
b0 /
b0 6
b0 8
1%
#660000
0%
#665000
b111110 4
1%
#670000
0%
#675000
b111111 4
1%
#680000
0%
#685000
b1000000 4
1%
#690000
0%
#695000
b1000001 4
1%
#700000
0%
#705000
b1000010 4
1%
#710000
0%
#715000
b1000011 4
1%
#720000
0%
#725000
b1000100 4
1%
#730000
0%
#735000
b1000101 4
1%
#740000
0%
#745000
b1000110 4
1%
#750000
0%
#755000
b1000111 4
1%
#760000
0%
#765000
b1001000 4
1%
#770000
0%
#775000
b1001001 4
1%
#780000
0%
#785000
b1001010 4
1%
#790000
0%
#795000
b1001011 4
1%
#800000
0%
#805000
b1001100 4
1%
#810000
0%
#815000
b1001101 4
1%
#820000
0%
#825000
b1001110 4
1%
#830000
0%
#835000
b1001111 4
1%
#840000
0%
#845000
b1010000 4
1%
#850000
0%
1'
1!
1+
#855000
b1010001 4
b11111111 .
b11111111 7
b11111111 ;
1$
1%
#860000
0%
#865000
b1010010 4
1%
#870000
0%
#875000
b1010011 4
1%
#880000
0%
#885000
b1010100 4
1%
#890000
0%
#895000
b1010101 4
1%
#900000
0%
#905000
b1010110 4
1%
#910000
0%
#915000
b1010111 4
1%
#920000
0%
#925000
b1011000 4
1%
#930000
0%
#935000
b1011001 4
1%
#940000
0%
#945000
b1011010 4
1%
#950000
0%
1(
0'
0!
0+
#955000
b1011011 4
0$
1%
#960000
0%
#965000
b1011100 4
1%
#970000
0%
#975000
b1011101 4
1%
#980000
0%
#985000
b1011110 4
1%
#990000
0%
#995000
b1011111 4
1%
#1000000
0%
#1005000
b1100000 4
1%
#1010000
0%
#1015000
b1100001 4
1%
#1020000
0%
#1025000
b1100010 4
1%
#1030000
0%
#1035000
b1100011 4
1%
#1040000
0%
#1045000
b1100100 4
1%
#1050000
0%
#1055000
b1100101 4
1%
#1060000
0%
#1065000
b1100110 4
1%
#1070000
0%
#1075000
b1100111 4
1%
#1080000
0%
#1085000
b1101000 4
1%
#1090000
0%
#1095000
b1101001 4
1%
#1100000
0%
#1105000
b1101010 4
1%
#1110000
0%
#1115000
b1101011 4
1%
#1120000
0%
#1125000
b1101100 4
1%
#1130000
0%
#1135000
b1101101 4
1%
#1140000
0%
#1145000
b1101110 4
1%
